{
  "generated_at": "2026-07-23T07:15:52.860577Z",
  "schema_version": 1,
  "config": {
    "season_code": "27W",
    "season_label": "Winter 2027",
    "is_live": true
  },
  "programs": [
    {
      "slug": "deakin-university",
      "university_name": "Deakin University",
      "program_name": "Australian Studies Summer School",
      "program_type": "ESP",
      "summer_open": false,
      "winter_open": false,
      "country": "Australia",
      "continent": "Asia/Oceania",
      "website": "https://www.deakin.edu.au/international-students/study-abroad-and-exchange#summer-school",
      "program_dates": "2027/01/03~2027/01/23",
      "nomination_deadline": "9/21",
      "application_deadline": "10/15",
      "program_fees": "Program cost: AUD $2,200\n *tuition fee waived\n*includes on-campus accommodation, airport pickup on arrival, a welcome dinner, a surf day and cultural excursions",
      "currency": "AUD",
      "scholarship_settlement": 1500000,
      "scholarship_tuition": "",
      "quota": 15,
      "quota_unit": "person",
      "accepts_undergrad": "Y",
      "accepts_grad": "N",
      "gpa_required": "2.8/4.3",
      "academic_system": "Trimester",
      "toefl_total": 69,
      "toefl_subscores": "Writing 21",
      "language_of_instruction_1": "English",
      "language_of_instruction_2": "",
      "lang2_level": "",
      "language_other_notes": "",
      "available_areas": "",
      "restricted_areas": "",
      "admission_notes": "",
      "academic_calendar": "",
      "housing_info": "",
      "housing_guaranteed": "Yes",
      "recent_factsheet": "",
      "additional_link": "",
      "campus_map_url": "",
      "transcript_info": "Transcripts usually arrive around March for Winter.",
      "notes": "",
      "cover_image_url": "https://commons.wikimedia.org/wiki/Special:FilePath/Deakin%20Worldly%20Strip%20Logo.jpg",
      "cover_image_credit": "Wikimedia Commons",
      "cover_image_kind": "logo",
      "campus_lat": -37.8475136,
      "campus_lng": 145.1149474
    },
    {
      "slug": "kwansei-gakuin-university",
      "university_name": "Kwansei Gakuin University",
      "program_name": "KGU Winter School 2027",
      "program_type": "ESP",
      "summer_open": false,
      "winter_open": false,
      "country": "Japan",
      "continent": "Asia/Oceania",
      "website": "https://ciec.kwansei.ac.jp/study/shortprograms/winterschool/",
      "program_dates": "2027/01/11~2027/01/29",
      "nomination_deadline": "9/30",
      "application_deadline": "10/31",
      "program_fees": "*2027 Program Cost: TBA\n- tuition fee waived\n\n*2026 Program Cost: tuition fee waived\n - Japanese Language Track: 185,000 JPY\n - Cultural Seminar Track: 210,000 JPY \n - Living expenses: 110,740 JPY",
      "currency": "JPY",
      "scholarship_settlement": 1000000,
      "scholarship_tuition": "",
      "quota": 10,
      "quota_unit": "person",
      "accepts_undergrad": "Y",
      "accepts_grad": "N",
      "gpa_required": "2.8/4.3",
      "academic_system": "Semester",
      "toefl_total": null,
      "toefl_subscores": "",
      "language_of_instruction_1": "English",
      "language_of_instruction_2": "Japanese",
      "lang2_level": "",
      "language_other_notes": "",
      "available_areas": "",
      "restricted_areas": "",
      "admission_notes": "",
      "academic_calendar": "",
      "housing_info": "",
      "housing_guaranteed": "Yes",
      "recent_factsheet": "",
      "additional_link": "",
      "campus_map_url": "",
      "transcript_info": "Transcripts usually arrive around March for Winter.",
      "notes": "",
      "cover_image_url": "https://commons.wikimedia.org/wiki/Special:FilePath/Kwansei%20Gakuin%20University%20logo.svg",
      "cover_image_credit": "Wikimedia Commons",
      "cover_image_kind": "logo",
      "campus_lat": 34.768813,
      "campus_lng": 135.3469101
    },
    {
      "slug": "sophia-university",
      "university_name": "Sophia University",
      "program_name": "January Session in Japanese Studies\n (On-site at Yotsuya Campus)",
      "program_type": "ESP",
      "summer_open": false,
      "winter_open": false,
      "country": "Japan",
      "continent": "Asia/Oceania",
      "website": "https://piloti.sophia.ac.jp/eng/studyabroad/short-term/january/",
      "program_dates": "2027/01/07~2027/01/29",
      "nomination_deadline": "10/08",
      "application_deadline": "10/15",
      "program_fees": "Program fee and application fee waived",
      "currency": "JPY",
      "scholarship_settlement": 1000000,
      "scholarship_tuition": "",
      "quota": 0,
      "quota_unit": "person",
      "accepts_undergrad": "Y",
      "accepts_grad": "N",
      "gpa_required": "3.01/4.3",
      "academic_system": "Semester",
      "toefl_total": 79,
      "toefl_subscores": "",
      "language_of_instruction_1": "English",
      "language_of_instruction_2": "Japanese",
      "lang2_level": "",
      "language_other_notes": "",
      "available_areas": "",
      "restricted_areas": "",
      "admission_notes": "",
      "academic_calendar": "",
      "housing_info": "",
      "housing_guaranteed": "No",
      "recent_factsheet": "",
      "additional_link": "",
      "campus_map_url": "",
      "transcript_info": "Transcripts usually arrive around February~March for Winter.",
      "notes": "The number of available spots will be announced shortly",
      "cover_image_url": "https://commons.wikimedia.org/wiki/Special:FilePath/Sophia%20University%20Yotsuya%20Campus%20%286459805535%29.jpg",
      "cover_image_credit": "Wikimedia Commons",
      "cover_image_kind": "photo",
      "campus_lat": 35.68395,
      "campus_lng": 139.7321744
    },
    {
      "slug": "katholieke-universiteit-leuven",
      "university_name": "Katholieke Universiteit Leuven",
      "program_name": "Winter University 2027 (On-site Program)",
      "program_type": "ESP",
      "summer_open": false,
      "winter_open": false,
      "country": "Belgium",
      "continent": "Europe",
      "website": "https://www.kuleuven.be/english/summer-schools/Global-Challenges-for-Our-Sustainable-Future",
      "program_dates": "2027/01/11~2027/01/29",
      "nomination_deadline": "TBA",
      "application_deadline": "11/01",
      "program_fees": "Registration fee for exchange students: €750\n*include tuition, social and cultural events and reading materials.",
      "currency": "EUR",
      "scholarship_settlement": 2000000,
      "scholarship_tuition": "",
      "quota": 0,
      "quota_unit": "person",
      "accepts_undergrad": "Y",
      "accepts_grad": "N",
      "gpa_required": "2.8/4.3",
      "academic_system": "Semester",
      "toefl_total": null,
      "toefl_subscores": "",
      "language_of_instruction_1": "English",
      "language_of_instruction_2": "",
      "lang2_level": "",
      "language_other_notes": "",
      "available_areas": "",
      "restricted_areas": "",
      "admission_notes": "Final year undergraduate",
      "academic_calendar": "",
      "housing_info": "",
      "housing_guaranteed": "Yes",
      "recent_factsheet": "",
      "additional_link": "",
      "campus_map_url": "",
      "transcript_info": "Transcripts usually arrive around February for Winter.",
      "notes": "The number of available spots will be announced shortly",
      "cover_image_url": "https://commons.wikimedia.org/wiki/Special:FilePath/KU%20Leuven%20logo.svg",
      "cover_image_credit": "Wikimedia Commons",
      "cover_image_kind": "logo",
      "campus_lat": 51.2205068,
      "campus_lng": 4.4046263
    },
    {
      "slug": "aalto-university-school-of-business",
      "university_name": "Aalto University - School of Business",
      "program_name": "Teaching period III (Jan-Feb) - Short Winter Exchange",
      "program_type": "ESP",
      "summer_open": false,
      "winter_open": false,
      "country": "Finland",
      "continent": "Europe",
      "website": "",
      "program_dates": "TBA(from early January to almost end of February)\n*7 weeks",
      "nomination_deadline": "TBA",
      "application_deadline": "TBA",
      "program_fees": "TBA\n*tuition fee waived",
      "currency": "EUR",
      "scholarship_settlement": 2000000,
      "scholarship_tuition": "",
      "quota": 0,
      "quota_unit": "person",
      "accepts_undergrad": "Y",
      "accepts_grad": "N",
      "gpa_required": "2.8/4.3",
      "academic_system": "Semester",
      "toefl_total": null,
      "toefl_subscores": "",
      "language_of_instruction_1": "English",
      "language_of_instruction_2": "",
      "lang2_level": "",
      "language_other_notes": "",
      "available_areas": "",
      "restricted_areas": "",
      "admission_notes": "",
      "academic_calendar": "",
      "housing_info": "",
      "housing_guaranteed": "TBA",
      "recent_factsheet": "",
      "additional_link": "",
      "campus_map_url": "",
      "transcript_info": "",
      "notes": "The number of available spots will be announced shortly",
      "cover_image_url": "https://commons.wikimedia.org/wiki/Special:FilePath/Aalto-yliopiston%20logo.svg",
      "cover_image_credit": "Wikimedia Commons",
      "cover_image_kind": "logo",
      "campus_lat": 60.1859118,
      "campus_lng": 24.8236392
    },
    {
      "slug": "universite-bordeaux-montaigne",
      "university_name": "Université Bordeaux Montaigne",
      "program_name": "Bordeaux Montaigne University International Winter School",
      "program_type": "ESP",
      "summer_open": false,
      "winter_open": false,
      "country": "France",
      "continent": "Europe",
      "website": "https://www.u-bordeaux-montaigne.fr/en/study/application/international-winter-school.html",
      "program_dates": "2027/02/14~2027/02/27",
      "nomination_deadline": "TBA",
      "application_deadline": "TBA",
      "program_fees": "TBA",
      "currency": "EUR",
      "scholarship_settlement": 2000000,
      "scholarship_tuition": "",
      "quota": 0,
      "quota_unit": "person",
      "accepts_undergrad": "Y",
      "accepts_grad": "N",
      "gpa_required": "2.8/4.3",
      "academic_system": "Semester",
      "toefl_total": null,
      "toefl_subscores": "",
      "language_of_instruction_1": "English",
      "language_of_instruction_2": "French",
      "lang2_level": "B1",
      "language_other_notes": "No language requirements for French language courses",
      "available_areas": "",
      "restricted_areas": "",
      "admission_notes": "",
      "academic_calendar": "",
      "housing_info": "",
      "housing_guaranteed": "Yes",
      "recent_factsheet": "",
      "additional_link": "",
      "campus_map_url": "",
      "transcript_info": "",
      "notes": "The number of available spots will be announced shortly",
      "cover_image_url": "https://commons.wikimedia.org/wiki/Special:FilePath/Universit%C3%A9%20Bordeaux%20Montaigne%20Logo.svg",
      "cover_image_credit": "Wikimedia Commons",
      "cover_image_kind": "logo",
      "campus_lat": 44.7949425,
      "campus_lng": -0.6173657
    },
    {
      "slug": "paris-school-of-business",
      "university_name": "Paris School of Business",
      "program_name": "Winter School 2027",
      "program_type": "VSP",
      "summer_open": false,
      "winter_open": false,
      "country": "France",
      "continent": "Europe",
      "website": "https://www.psbedu.paris/en/programs/short-programs",
      "program_dates": "2027/01/04~2027/01/15",
      "nomination_deadline": "9/30",
      "application_deadline": "11/15",
      "program_fees": "Tuition fee + Hospitality package = €2,835\n (The full package includes: Individual accommodation in a residence / Daily breakfast and lunches on weekdays / All activities and cultural visits / Farewell dinner)",
      "currency": "EUR",
      "scholarship_settlement": 2000000,
      "scholarship_tuition": "등록금 반액 수준(추후 안내)\nApproximately 50% of the tuition fee (details to be announced later)",
      "quota": 6,
      "quota_unit": "person",
      "accepts_undergrad": "Y",
      "accepts_grad": "N",
      "gpa_required": "2.8/4.3",
      "academic_system": "Semester",
      "toefl_total": 80,
      "toefl_subscores": "",
      "language_of_instruction_1": "English",
      "language_of_instruction_2": "",
      "lang2_level": "B2",
      "language_other_notes": "",
      "available_areas": "",
      "restricted_areas": "",
      "admission_notes": "",
      "academic_calendar": "",
      "housing_info": "",
      "housing_guaranteed": "Yes",
      "recent_factsheet": "",
      "additional_link": "",
      "campus_map_url": "",
      "transcript_info": "Transcripts usually arrive around March for Winter.",
      "notes": "",
      "cover_image_url": "https://commons.wikimedia.org/wiki/Special:FilePath/Paris%20School%20of%20Business%20%28PSB%29%20logo.svg",
      "cover_image_credit": "Wikimedia Commons",
      "cover_image_kind": "logo",
      "campus_lat": null,
      "campus_lng": null
    },
    {
      "slug": "free-university-of-berlin",
      "university_name": "Free University of Berlin",
      "program_name": "FUBiS Term I 2027",
      "program_type": "VSP",
      "summer_open": false,
      "winter_open": false,
      "country": "Germany",
      "continent": "Europe",
      "website": "https://www.fubis.org/index.html",
      "program_dates": "2027/01/04~2027/01/22",
      "nomination_deadline": "9/30",
      "application_deadline": "11/23",
      "program_fees": "425 EUR program fee(350 EUR with the early registration discount)\n +\n 1,475 EUR tuition fee\n +\n housing(2027 fees still tbc)",
      "currency": "EUR",
      "scholarship_settlement": 2000000,
      "scholarship_tuition": "등록금 반액 수준(추후 안내)\nApproximately 50% of the tuition fee (details to be announced later)",
      "quota": 4,
      "quota_unit": "person",
      "accepts_undergrad": "Y",
      "accepts_grad": "N",
      "gpa_required": "2.8/4.3",
      "academic_system": "Semester",
      "toefl_total": null,
      "toefl_subscores": "",
      "language_of_instruction_1": "English",
      "language_of_instruction_2": "German",
      "lang2_level": "B2",
      "language_other_notes": "",
      "available_areas": "",
      "restricted_areas": "",
      "admission_notes": "",
      "academic_calendar": "",
      "housing_info": "",
      "housing_guaranteed": "Yes",
      "recent_factsheet": "",
      "additional_link": "",
      "campus_map_url": "",
      "transcript_info": "Transcripts usually arrive around February~March for Winter.",
      "notes": "",
      "cover_image_url": "https://commons.wikimedia.org/wiki/Special:FilePath/Freie%20Universit%C3%A4t%20Berlin%20Logo%2005.2024.svg",
      "cover_image_credit": "Wikimedia Commons",
      "cover_image_kind": "logo",
      "campus_lat": null,
      "campus_lng": null
    },
    {
      "slug": "universita-cattolica-del-sacro-cuore",
      "university_name": "Università Cattolica del Sacro Cuore",
      "program_name": "Winter Programmes 2026-2027",
      "program_type": "VSP",
      "summer_open": false,
      "winter_open": false,
      "country": "Italy",
      "continent": "Europe",
      "website": "https://international.unicatt.it/ucscinternational-short-term-programs-winter-programs",
      "program_dates": "2027/01/05~2027/01/15\n2027/01/05~2027/01/22\n2027/01/18~2027/01/29\n*schedule varies by course",
      "nomination_deadline": "10/24",
      "application_deadline": "11/01",
      "program_fees": "Tuition fees:\nApplication fee: € 75\nOne course: € 1,550\nTwo courses: € 2,900\n\nOff- Campus Apartments /  Residence (Double Room):\n2-week session: € 700\n3-week session: € 1.050",
      "currency": "EUR",
      "scholarship_settlement": 2000000,
      "scholarship_tuition": "등록금 반액 수준(추후 안내)\nApproximately 50% of the tuition fee (details to be announced later)",
      "quota": 4,
      "quota_unit": "person",
      "accepts_undergrad": "Y",
      "accepts_grad": "N",
      "gpa_required": "2.96/4.3",
      "academic_system": "Semester",
      "toefl_total": 79,
      "toefl_subscores": "",
      "language_of_instruction_1": "English",
      "language_of_instruction_2": "",
      "lang2_level": "B2",
      "language_other_notes": "",
      "available_areas": "",
      "restricted_areas": "",
      "admission_notes": "",
      "academic_calendar": "",
      "housing_info": "",
      "housing_guaranteed": "Yes",
      "recent_factsheet": "",
      "additional_link": "",
      "campus_map_url": "",
      "transcript_info": "Transcripts usually arrive around February for Winter.",
      "notes": "",
      "cover_image_url": "",
      "cover_image_credit": "",
      "cover_image_kind": "",
      "campus_lat": null,
      "campus_lng": null
    },
    {
      "slug": "humboldt-university-of-berlin",
      "university_name": "Humboldt University of Berlin",
      "program_name": "the Humboldt Winter and Summer University (HUWISU)",
      "program_type": "VSP",
      "summer_open": false,
      "winter_open": false,
      "country": "Germany",
      "continent": "Europe",
      "website": "https://hic.hu-berlin.de/en/huwisu",
      "program_dates": "TBA",
      "nomination_deadline": "TBA",
      "application_deadline": "TBA",
      "program_fees": "TBA",
      "currency": "EUR",
      "scholarship_settlement": 2000000,
      "scholarship_tuition": "등록금 반액 수준(추후 안내)\nApproximately 50% of the tuition fee (details to be announced later)",
      "quota": 4,
      "quota_unit": "person",
      "accepts_undergrad": "Y",
      "accepts_grad": "N",
      "gpa_required": "2.8/4.3",
      "academic_system": "Semester",
      "toefl_total": 90,
      "toefl_subscores": "minimum 20 in each section",
      "language_of_instruction_1": "English",
      "language_of_instruction_2": "German",
      "lang2_level": "",
      "language_other_notes": "A letter of motivation is required for the English-language subject courses.\nA German language certificate is required for the language courses and German-language subject courses. A language assessment is required for this in the course of online registration. The course levels are based on the Common European Framework of Reference for Language requirements.",
      "available_areas": "",
      "restricted_areas": "",
      "admission_notes": "",
      "academic_calendar": "",
      "housing_info": "",
      "housing_guaranteed": "No",
      "recent_factsheet": "",
      "additional_link": "",
      "campus_map_url": "",
      "transcript_info": "Transcripts usually arrive around February~March for Winter.",
      "notes": "",
      "cover_image_url": "https://commons.wikimedia.org/wiki/Special:FilePath/Huberlin-logo.svg",
      "cover_image_credit": "Wikimedia Commons",
      "cover_image_kind": "logo",
      "campus_lat": 52.5183402,
      "campus_lng": 13.3929202
    },
    {
      "slug": "waseda-university",
      "university_name": "Waseda University",
      "program_name": "Waseda Winter Session 2027",
      "program_type": "VSP",
      "summer_open": false,
      "winter_open": false,
      "country": "Japan",
      "continent": "Asia/Oceania",
      "website": "https://www.waseda.jp/inst/gip/winter-session",
      "program_dates": "2027/01/11~2027/02/02",
      "nomination_deadline": "9/18",
      "application_deadline": "10/02",
      "program_fees": "2 Courses with housing: JPY 557,000\n 2 Courses without housing: JPY 365,000",
      "currency": "JPY",
      "scholarship_settlement": 1000000,
      "scholarship_tuition": "등록금 반액 수준(추후 안내)\nApproximately 50% of the tuition fee (details to be announced later)",
      "quota": 2,
      "quota_unit": "person",
      "accepts_undergrad": "Y",
      "accepts_grad": "N",
      "gpa_required": "2.8/4.3",
      "academic_system": "Semester",
      "toefl_total": 79,
      "toefl_subscores": "",
      "language_of_instruction_1": "English",
      "language_of_instruction_2": "",
      "lang2_level": "",
      "language_other_notes": "",
      "available_areas": "",
      "restricted_areas": "",
      "admission_notes": "",
      "academic_calendar": "",
      "housing_info": "",
      "housing_guaranteed": "Yes",
      "recent_factsheet": "",
      "additional_link": "",
      "campus_map_url": "",
      "transcript_info": "",
      "notes": "",
      "cover_image_url": "https://commons.wikimedia.org/wiki/Special:FilePath/Waseda.png",
      "cover_image_credit": "Wikimedia Commons",
      "cover_image_kind": "logo",
      "campus_lat": 35.7091798,
      "campus_lng": 139.7197213
    },
    {
      "slug": "institut-d-etudes-politiques-de-paris",
      "university_name": "Institut d'études politiques de Paris",
      "program_name": "Winter School 2027",
      "program_type": "VSP",
      "summer_open": false,
      "winter_open": false,
      "country": "France",
      "continent": "Europe",
      "website": "https://www.sciencespo.fr/international-short-programmes/en/winter-school/",
      "program_dates": "2027/01/18~2027/01/29",
      "nomination_deadline": "9/30",
      "application_deadline": "10/14",
      "program_fees": "Main track: 1,950 €\nOptional elective: 1,950 €\nHousing: 700~1,200 €",
      "currency": "EUR",
      "scholarship_settlement": 2000000,
      "scholarship_tuition": "등록금 반액 수준(추후 안내)\nApproximately 50% of the tuition fee (details to be announced later)",
      "quota": 5,
      "quota_unit": "person",
      "accepts_undergrad": "Y",
      "accepts_grad": "N",
      "gpa_required": "2.8/4.3",
      "academic_system": "Semester",
      "toefl_total": 90,
      "toefl_subscores": "R+L minimum 46, S+W minimum 44 (120 scale)\naverage of R and L: 5.0 & average of S and W: 4.5 (6 scale)",
      "language_of_instruction_1": "English",
      "language_of_instruction_2": "",
      "lang2_level": "",
      "language_other_notes": "",
      "available_areas": "",
      "restricted_areas": "",
      "admission_notes": "",
      "academic_calendar": "",
      "housing_info": "",
      "housing_guaranteed": "Yes",
      "recent_factsheet": "",
      "additional_link": "",
      "campus_map_url": "",
      "transcript_info": "",
      "notes": "",
      "cover_image_url": "https://commons.wikimedia.org/wiki/Special:FilePath/Logo%20Sciences%20Po.svg",
      "cover_image_credit": "Wikimedia Commons",
      "cover_image_kind": "logo",
      "campus_lat": 48.8538978,
      "campus_lng": 2.3290212
    }
  ]
}